{"type":"Topology","objects":{"GN_6148":{"type":"GeometryCollection","bbox":[80.07327638996254,7.4991555181429606,80.22058455780225,7.619451711637884],"geometries":[{"type":"MultiPolygon","properties":{"SP_ID":"358","gid":5282,"name":"Kandegedara","code":"6148140","gnnum":"1380","gnd_n":"Kandegedara","prov_c":"6","dis_c":"61","dsd_c":"6148","gnd_c":"6148140"},"arcs":[[[0,1]],[[2,3,4,5,6,7]]]},{"type":"Polygon","properties":{"SP_ID":"4172","gid":5279,"name":"Henegedara","code":"6148105","gnnum":"1407","gnd_n":"Henegedara","prov_c":"6","dis_c":"61","dsd_c":"6148","gnd_c":"6148105"},"arcs":[[8,9,10,11,12]]},{"type":"Polygon","properties":{"SP_ID":"4511","gid":5296,"name":"Palavitiya","code":"6148040","gnnum":"1369","gnd_n":"Palavitiya","prov_c":"6","dis_c":"61","dsd_c":"6148","gnd_c":"6148040"},"arcs":[[13,14,15,16,17]]},{"type":"Polygon","properties":{"SP_ID":"4883","gid":5297,"name":"Ranorawa","code":"6148055","gnnum":"1365","gnd_n":"Ranorawa","prov_c":"6","dis_c":"61","dsd_c":"6148","gnd_c":"6148055"},"arcs":[[18,19,20,21]]},{"type":"Polygon","properties":{"SP_ID":"5189","gid":5272,"name":"Bodhimulla","code":"6148170","gnnum":"1403","gnd_n":"Bodhimulla","prov_c":"6","dis_c":"61","dsd_c":"6148","gnd_c":"6148170"},"arcs":[[22,23,24,25,26,27]]},{"type":"Polygon","properties":{"SP_ID":"5356","gid":5273,"name":"Dematawa","code":"6148095","gnnum":"1385","gnd_n":"Dematawa","prov_c":"6","dis_c":"61","dsd_c":"6148","gnd_c":"6148095"},"arcs":[[28,29,30,-10,31]]},{"type":"Polygon","properties":{"SP_ID":"5498","gid":5268,"name":"Adukkane","code":"6148150","gnnum":"1392","gnd_n":"Adukkane","prov_c":"6","dis_c":"61","dsd_c":"6148","gnd_c":"6148150"},"arcs":[[-5,32,33,34,35,36]]},{"type":"Polygon","properties":{"SP_ID":"5499","gid":5269,"name":"Angamuwa","code":"6148115","gnnum":"1386","gnd_n":"Angamuwa","prov_c":"6","dis_c":"61","dsd_c":"6148","gnd_c":"6148115"},"arcs":[[37,38,39,-11,-31]]},{"type":"Polygon","properties":{"SP_ID":"5500","gid":5270,"name":"Anukkanhena","code":"6148120","gnnum":"1406","gnd_n":"Anukkanhena","prov_c":"6","dis_c":"61","dsd_c":"6148","gnd_c":"6148120"},"arcs":[[40,41,42,43,44,45,-39]]},{"type":"Polygon","properties":{"SP_ID":"5501","gid":5271,"name":"Beddegama","code":"6148080","gnnum":"1376","gnd_n":"Beddegama","prov_c":"6","dis_c":"61","dsd_c":"6148","gnd_c":"6148080"},"arcs":[[46,47,48,49,50]]},{"type":"Polygon","properties":{"SP_ID":"5502","gid":5274,"name":"Dunupotha","code":"6148075","gnnum":"1368","gnd_n":"Dunupotha","prov_c":"6","dis_c":"61","dsd_c":"6148","gnd_c":"6148075"},"arcs":[[51,52,53,-48,54]]},{"type":"Polygon","properties":{"SP_ID":"5503","gid":5275,"name":"Galagedara","code":"6148145","gnnum":"1381","gnd_n":"Galagedara","prov_c":"6","dis_c":"61","dsd_c":"6148","gnd_c":"6148145"},"arcs":[[-37,55,56,-6]]},{"type":"Polygon","properties":{"SP_ID":"5504","gid":5276,"name":"Gallehepitiya","code":"6148050","gnnum":"1362","gnd_n":"Gallehepitiya","prov_c":"6","dis_c":"61","dsd_c":"6148","gnd_c":"6148050"},"arcs":[[-22,57,58]]},{"type":"Polygon","properties":{"SP_ID":"5505","gid":5277,"name":"Gonnawa","code":"6148165","gnnum":"1388","gnd_n":"Gonnawa","prov_c":"6","dis_c":"61","dsd_c":"6148","gnd_c":"6148165"},"arcs":[[59,60,-23,-45,61]]},{"type":"Polygon","properties":{"SP_ID":"5506","gid":5278,"name":"Hanwella","code":"6148035","gnnum":"1374","gnd_n":"Hanwella","prov_c":"6","dis_c":"61","dsd_c":"6148","gnd_c":"6148035"},"arcs":[[-16,62,-55,-47,63,64]]},{"type":"Polygon","properties":{"SP_ID":"5507","gid":5280,"name":"Hindawa","code":"6148190","gnnum":"1391","gnd_n":"Hindawa","prov_c":"6","dis_c":"61","dsd_c":"6148","gnd_c":"6148190"},"arcs":[[65,66,67,68,-34]]},{"type":"Polygon","properties":{"SP_ID":"5508","gid":5281,"name":"Kanapothuhera","code":"6148130","gnnum":"1382","gnd_n":"Kanapothuhera","prov_c":"6","dis_c":"61","dsd_c":"6148","gnd_c":"6148130"},"arcs":[[69,-7,-57,70,71,72]]},{"type":"Polygon","properties":{"SP_ID":"5509","gid":5283,"name":"Kanduboda","code":"6148100","gnnum":"1410","gnd_n":"Kanduboda","prov_c":"6","dis_c":"61","dsd_c":"6148","gnd_c":"6148100"},"arcs":[[73,74,-32,-9,75]]},{"type":"Polygon","properties":{"SP_ID":"5510","gid":5284,"name":"Kanogama","code":"6148135","gnnum":"1379","gnd_n":"Kanogama","prov_c":"6","dis_c":"61","dsd_c":"6148","gnd_c":"6148135"},"arcs":[[76,-2,77,-8,-70,78]]},{"type":"Polygon","properties":{"SP_ID":"5511","gid":5285,"name":"Kanoyaya","code":"6148195","gnnum":"1390","gnd_n":"Kanoyaya","prov_c":"6","dis_c":"61","dsd_c":"6148","gnd_c":"6148195"},"arcs":[[79,-66,-33,-4]]},{"type":"Polygon","properties":{"SP_ID":"5512","gid":5286,"name":"Katumuluwa","code":"6148060","gnnum":"1364","gnd_n":"Katumuluwa","prov_c":"6","dis_c":"61","dsd_c":"6148","gnd_c":"6148060"},"arcs":[[80,81,82,-20]]},{"type":"Polygon","properties":{"SP_ID":"5513","gid":5287,"name":"Kolambagama","code":"6148045","gnnum":"1363","gnd_n":"Kolambagama","prov_c":"6","dis_c":"61","dsd_c":"6148","gnd_c":"6148045"},"arcs":[[-21,-83,83,-18,84,-58]]},{"type":"Polygon","properties":{"SP_ID":"5514","gid":5288,"name":"Kosdeniya","code":"6148025","gnnum":"1377","gnd_n":"Kosdeniya","prov_c":"6","dis_c":"61","dsd_c":"6148","gnd_c":"6148025"},"arcs":[[85,-50,86,87,-29,-75,88,89]]},{"type":"Polygon","properties":{"SP_ID":"5515","gid":5289,"name":"Magulagama","code":"6148110","gnnum":"1408","gnd_n":"Magulagama","prov_c":"6","dis_c":"61","dsd_c":"6148","gnd_c":"6148110"},"arcs":[[-40,-46,-28,90,-12]]},{"type":"Polygon","properties":{"SP_ID":"5516","gid":5290,"name":"Maveehena","code":"6148065","gnnum":"1367","gnd_n":"Maveehena","prov_c":"6","dis_c":"61","dsd_c":"6148","gnd_c":"6148065"},"arcs":[[-82,91,92,-14,-84]]},{"type":"Polygon","properties":{"SP_ID":"5517","gid":5291,"name":"Medagama","code":"6148020","gnnum":"1375","gnd_n":"Medagama","prov_c":"6","dis_c":"61","dsd_c":"6148","gnd_c":"6148020"},"arcs":[[-89,-74,93]]},{"type":"Polygon","properties":{"SP_ID":"5518","gid":5292,"name":"Moragane","code":"6148125","gnnum":"1383","gnd_n":"Moragane","prov_c":"6","dis_c":"61","dsd_c":"6148","gnd_c":"6148125"},"arcs":[[94,-72,95,-42,96]]},{"type":"Polygon","properties":{"SP_ID":"5519","gid":5294,"name":"Nelibewa","code":"6148090","gnnum":"1384","gnd_n":"Nelibewa","prov_c":"6","dis_c":"61","dsd_c":"6148","gnd_c":"6148090"},"arcs":[[97,-97,-41,-38,-30,-88]]},{"type":"Polygon","properties":{"SP_ID":"5521","gid":5295,"name":"Nindawela","code":"6148175","gnnum":"1404","gnd_n":"Nindawela","prov_c":"6","dis_c":"61","dsd_c":"6148","gnd_c":"6148175"},"arcs":[[-26,98]]},{"type":"Polygon","properties":{"SP_ID":"5522","gid":5298,"name":"Rathmalla","code":"6148070","gnnum":"1366","gnd_n":"Rathmalla","prov_c":"6","dis_c":"61","dsd_c":"6148","gnd_c":"6148070"},"arcs":[[-93,99,-52,-63,-15]]},{"type":"Polygon","properties":{"SP_ID":"5523","gid":5301,"name":"Thissawa","code":"6148085","gnnum":"1378","gnd_n":"Thissawa","prov_c":"6","dis_c":"61","dsd_c":"6148","gnd_c":"6148085"},"arcs":[[100,-79,-73,-95,-98,-87,-49,-54]]},{"type":"Polygon","properties":{"SP_ID":"5525","gid":5302,"name":"Udugampalagedara","code":"6148155","gnnum":"1393","gnd_n":"Udugampalagedara","prov_c":"6","dis_c":"61","dsd_c":"6148","gnd_c":"6148155"},"arcs":[[-56,-36,101,-43,-96,-71]]},{"type":"Polygon","properties":{"SP_ID":"5526","gid":5303,"name":"Weliwehera","code":"6148160","gnnum":"1389","gnd_n":"Weliwehera","prov_c":"6","dis_c":"61","dsd_c":"6148","gnd_c":"6148160"},"arcs":[[-35,-69,102,-62,-44,-102]]},{"type":"Polygon","properties":{"SP_ID":"5527","gid":5304,"name":"Wetehepitiya","code":"6148185","gnnum":"1394","gnd_n":"Wetehepitiya","prov_c":"6","dis_c":"61","dsd_c":"6148","gnd_c":"6148185"},"arcs":[[-103,-68,103,104,-60]]},{"type":"Polygon","properties":{"SP_ID":"5528","gid":5305,"name":"Wijaya Udagama","code":"6148180","gnnum":"1387","gnd_n":"Wijaya Udagama","prov_c":"6","dis_c":"61","dsd_c":"6148","gnd_c":"6148180"},"arcs":[[105,-24,-61,-105]]},{"type":"Polygon","properties":{"SP_ID":"5530","gid":5306,"name":"Wilbagedara","code":"6148030","gnnum":"1373","gnd_n":"Wilbagedara","prov_c":"6","dis_c":"61","dsd_c":"6148","gnd_c":"6148030"},"arcs":[[-64,-51,-86,106]]}]}},"arcs":[[[6876,3935],[-91,-77],[-45,-83],[-74,-105],[-11,-55],[-37,-80],[-23,-40]],[[6595,3495],[-6,39],[-16,62],[-31,80],[-22,57],[-31,82],[4,72],[16,33],[37,12],[71,-7],[21,-5],[36,2],[25,50],[20,87],[45,18],[53,-57],[59,-85]],[[6328,3131],[-40,-111],[-22,-112],[-17,-69],[-6,-84],[6,-90],[2,-17],[9,-66],[-142,-260],[-56,-102],[-171,-237],[-15,-14],[-161,-146],[-173,-101],[-5,-5]],[[5537,1717],[-8,35],[-17,89]],[[5512,1841],[-12,59],[0,225],[-6,84],[0,42],[40,42],[41,-7],[28,49],[-23,78],[-74,35],[-35,147],[-6,24]],[[5465,2619],[17,25],[46,49],[98,43],[23,21],[-6,98],[-40,127],[-18,63],[35,63],[23,63],[-41,120],[-6,84],[12,98],[-11,25]],[[5597,3498],[22,38],[6,64],[17,21],[4,1]],[[5646,3622],[19,6],[86,-98],[81,-281],[29,-218],[69,-253],[12,-26],[28,46],[47,77],[55,78],[88,97],[87,57],[81,24]],[[1880,6148],[19,0],[33,-160],[-16,-261],[33,-70],[74,-10],[90,-70],[164,-120],[17,-100],[57,-140],[8,-29]],[[2359,5188],[-20,-6],[-106,-71],[-1,-16]],[[2232,5095],[-7,-144],[41,-70],[90,-90],[33,-151],[17,-130]],[[2406,4510],[-67,-27],[-105,2],[-129,0],[-98,0],[-60,0],[-54,0],[-51,3],[-28,8],[-34,3],[-26,12],[-46,18],[-49,50],[-107,20],[-131,-21],[-197,10],[-19,-23]],[[1205,4565],[-1,18],[-9,211],[-8,110],[-25,160],[-17,-29],[1,9],[24,140],[66,81],[115,60],[32,60],[-41,151],[-33,130],[8,130],[49,50],[-33,90],[-57,40],[-49,60],[-25,81],[-17,100],[49,90],[52,91],[30,20],[9,-5],[32,-15],[66,-40],[66,-70],[33,-131],[131,-50],[98,41],[129,0]],[[8291,8289],[4,7],[35,-176],[12,-98],[-23,-49],[-41,-43],[-86,-147],[-11,-92],[17,-98],[46,-63],[-5,-105],[-58,-36],[-40,-14],[-5,1]],[[8136,7376],[-156,27],[-230,21],[-172,-29],[-109,-66]],[[7469,7329],[0,52],[-70,70],[-34,127],[-6,112],[-46,84],[11,120],[12,77],[-58,7],[-80,-21],[-63,-57],[-58,-56],[-57,0],[-46,35],[-19,111]],[[6955,7990],[10,-6],[40,-14],[23,7],[6,64],[-46,119],[-69,56],[-29,63],[6,56],[40,71],[115,105],[149,29],[89,7],[63,0],[6,15]],[[7358,8562],[126,-15],[58,7],[115,92],[63,21],[29,-42],[52,-91],[57,-7],[35,-35],[0,-113],[63,-126],[144,-56],[92,21],[69,28],[30,43]],[[9967,8853],[9,0],[23,-42],[-17,-98],[-17,-78],[11,-98],[0,-42],[0,-63],[-34,-78],[-11,-70],[-6,-42],[-46,-49],[-40,-134],[-11,-168],[-38,-85],[-17,-56],[-40,-35],[-29,-35],[0,-127],[0,-70],[0,-112],[12,-35],[2,-28],[4,-43],[-52,-47]],[[9670,7218],[-34,96],[-70,225],[-28,105],[-41,49],[-126,204],[-75,84],[-58,35],[-109,140],[-115,204],[-121,260],[-13,12]],[[8880,8632],[18,16],[29,98],[-23,140],[5,141]],[[8909,9027],[32,-42],[52,-7],[34,35],[6,120],[0,98],[40,84],[40,14],[29,7],[69,-91],[104,-140],[51,-14],[64,-28],[92,-49],[86,-70],[52,-28],[103,-84],[23,-21],[23,-7],[29,28],[52,35],[51,-14],[26,0]],[[1850,2722],[133,-193],[15,-79],[29,-61],[21,-88],[15,-44],[14,-79],[-21,-61],[-86,-290],[-43,-185],[0,-44],[43,-201],[0,-119]],[[1970,1278],[0,-4],[-43,-200]],[[1927,1074],[-27,37],[-24,36],[-24,0],[-113,-95],[-130,-153],[-56,-18],[-10,-4],[-24,22],[-59,44],[-18,43],[-30,51],[-12,29],[-24,15],[-50,58],[-42,65],[0,51],[-12,51],[-36,44],[-11,-4]],[[1225,1346],[-35,204],[-3,130],[-19,42],[-85,28],[-82,90],[-48,159],[-42,141],[-20,74],[2,62],[17,65],[-65,100],[-6,4]],[[839,2445],[3,7],[40,111],[-49,233]],[[833,2796],[79,-27],[70,-20],[81,1],[102,0],[60,39],[21,53],[33,86],[43,86],[60,41],[58,-60],[82,-30],[74,-40],[115,-150],[131,-50],[8,-3]],[[3702,6228],[-6,-17],[2,-6]],[[3698,6205],[19,-56],[44,-158],[-14,-193],[-7,-202],[-22,-149],[-71,-176],[-158,-220],[-111,-96],[-170,-70]],[[3208,4885],[-36,133],[-82,160],[-189,60],[-181,29],[-131,-110],[-196,-71],[-99,-10],[-62,19]],[[2359,5188],[13,4],[57,80],[131,341],[180,241],[107,80],[131,41],[139,-10],[91,0],[90,40],[135,56],[148,110],[82,60],[39,-3]],[[5512,1841],[-102,-33],[-64,-40],[-44,-46],[-63,-100],[-47,-81],[-26,-26],[-19,-8],[-37,0],[-24,25],[-16,12],[-12,0],[-14,-23],[-70,-80],[-28,-18],[-19,3],[-28,34],[-19,20],[-14,61],[-17,5],[-82,-27]],[[4767,1519],[15,71],[18,91],[22,91],[-5,84],[0,92],[-6,119],[-23,49],[-29,35],[-40,7],[-46,-7],[-46,-42],[-41,-28],[-57,0],[-52,28],[-23,56],[-92,42],[-52,21],[-22,5],[-64,-19],[-69,-78]],[[4155,2136],[-11,28],[-7,48],[-10,67],[-7,54],[-11,59],[-5,52],[-7,36]],[[4097,2480],[52,7],[53,41],[75,46],[75,46],[44,29],[55,13],[53,0],[43,-14]],[[4547,2648],[33,9],[69,-49],[52,28],[51,21],[58,0],[29,-56],[23,-91],[57,42],[35,-14],[23,-70],[57,-7],[58,98],[51,57],[52,14],[103,49],[81,21],[34,7],[41,-42],[11,-46]],[[3208,4885],[-24,-10],[-22,-44],[-36,-70],[51,-105],[101,-176],[0,-61],[-29,-114],[-72,-264],[8,-114],[10,-24]],[[3195,3903],[-67,-33],[-237,-201],[-140,-70],[-49,-10],[-66,-1],[-49,10],[-74,50],[-74,90],[-57,70],[-123,121],[-15,7]],[[2244,3936],[56,153],[81,281],[25,140]],[[3195,3903],[11,-29],[36,-52],[44,-26],[36,-27],[79,-26],[35,0],[101,-8],[50,-53],[36,0],[22,-10]],[[3645,3672],[14,-7],[36,-123],[15,-53],[-39,-126]],[[3671,3363],[-4,-14],[-65,-88],[-99,-65]],[[3503,3196],[-8,-6],[-72,-61],[-57,-176],[-51,-44],[-71,-18],[-29,9],[-79,35],[-72,26],[-72,-44],[-86,-53]],[[2906,2864],[-14,-8],[-58,-1],[-50,-35],[-47,-61],[-64,-44],[-58,26],[-36,-18],[-21,-52],[-36,-79],[-43,-27],[-29,9],[-21,26],[-72,35],[-51,-9],[-64,26],[-87,88],[-50,44],[-50,-18],[-50,-35],[-7,-61],[-66,25],[-82,27]],[[1850,2722],[0,23],[-8,140],[-9,131],[0,100],[-8,60],[0,60],[49,40],[33,30],[32,191],[-8,80],[16,70],[50,51],[57,20],[66,10],[49,30],[57,130],[18,48]],[[6194,6678],[37,-57],[138,-98],[17,-78],[25,-119]],[[6411,6326],[4,-21],[23,-162],[77,-81]],[[6515,6062],[-82,-59],[-92,-148],[-103,-211],[-46,-119],[-86,-77],[-41,-57],[-17,-112],[-57,-92],[-69,42],[-144,0],[-28,-35],[-46,-28],[-41,21],[-29,119],[-11,204],[-121,70],[-75,21],[-138,34]],[[5289,5635],[0,1],[-17,56],[-40,63],[28,183],[35,98],[80,28],[23,85],[46,35],[40,21],[-35,126],[35,106],[157,362]],[[5641,6799],[20,3],[144,-21],[75,-14],[46,-28],[34,-21],[35,15],[46,14],[29,0],[17,-21],[29,-42],[28,-7],[46,-7],[4,8]],[[7348,7140],[23,-12],[40,-63],[58,35],[69,-14],[46,-28],[57,-77],[35,-133],[12,-211],[3,-98],[34,-134],[116,-245],[138,-309],[-7,-5]],[[7972,5846],[-45,-30],[-63,-78],[-17,-63],[-29,-42],[-46,-35],[-11,-70],[6,-106],[-29,-56],[-23,-7],[-184,-106],[-138,-56],[-40,-14],[-40,-14],[-22,6]],[[7291,5175],[-7,29],[-35,140],[-28,141],[-202,168],[-161,140],[-69,63],[-121,105],[-98,77],[-40,35],[-15,-11]],[[6411,6326],[254,183],[356,296],[252,267],[58,77],[17,-9]],[[4547,2648],[-111,110],[-45,86],[-18,150],[3,96],[-2,62]],[[4374,3152],[27,-39],[35,7],[34,28],[35,28],[115,-14],[40,64],[40,63],[29,49],[103,92],[34,14],[75,0],[-6,-42],[24,-56],[40,0],[28,49],[23,49],[23,28],[41,-14],[46,-49],[40,-28],[63,-35],[29,21],[29,28],[57,-7],[29,-6],[29,14],[28,14],[40,56],[41,21],[46,0],[6,11]],[[8909,9027],[-11,14],[-58,7],[-40,35],[-46,35],[-86,28],[-63,28],[-52,14],[-81,35],[-46,42],[-34,56],[-35,98],[-40,21],[-29,0],[-63,-14],[-99,-45]],[[8126,9381],[-11,142],[-26,191],[52,127],[100,158],[32,-56],[117,-108],[41,0],[75,8],[89,51],[120,22],[17,3],[61,-17],[41,-25],[35,-66],[48,-51],[75,-50],[110,-33],[212,-33],[137,-25],[139,-54],[11,-4],[117,-59],[103,-66],[27,-75],[21,-109],[0,-92],[14,-109],[34,-100],[50,-98]],[[3246,1966],[-27,-35],[-63,-21],[-81,-22],[-115,0],[-51,28],[-81,28],[-29,-14],[-34,-42],[-29,7],[-17,35],[-29,70],[-29,42],[-51,28],[-92,14],[-64,-7],[12,-49],[34,-84],[6,-85],[-17,-21],[-11,-84],[0,-98],[46,-35],[34,-64],[6,-56],[12,-133],[-11,-84],[-3,-40]],[[2562,1244],[-3,-10],[-69,-56],[-35,-7],[-46,21],[-69,7],[-34,-14],[-109,35],[-23,-21],[-46,-1],[-115,49],[-43,31]],[[2906,2864],[88,-210],[75,-169],[63,-77],[86,-35],[75,-42],[18,-203],[-12,-92],[-53,-70]],[[7469,7329],[0,-4],[-121,-127],[0,-58]],[[6194,6678],[37,97],[34,113],[97,147],[41,85],[63,231],[28,225],[17,225],[17,70],[46,42],[52,29],[28,63],[15,27]],[[6669,8032],[8,15],[115,21],[87,-35],[76,-43]],[[4767,1519],[-7,-35],[-23,-267],[23,-253],[29,-105],[-17,-42],[-86,-91],[-52,-50],[-6,-49],[1,-77],[-29,-21],[-46,-14],[-35,-29],[-23,-49],[-17,-70],[-23,-98],[-63,-155],[-15,-27]],[[4378,87],[-6,2],[-35,-7],[-36,-15],[-48,8],[-41,14],[-30,29],[-36,44],[-18,43],[-18,29],[-45,37],[-35,-15],[-66,29],[-53,44],[-18,65],[-18,36],[-48,44],[-71,22],[-42,22],[-30,14],[0,58],[18,29],[0,22],[12,37],[-18,36],[-10,4]],[[3686,718],[0,34],[-52,70],[11,42],[115,21],[98,43],[138,105],[80,36],[23,35],[46,63],[6,98],[-29,169],[0,168],[11,85],[-5,51]],[[4128,1738],[-7,68],[-6,211],[40,119]],[[5525,4170],[30,-16],[23,-70],[41,-126],[29,-70],[5,-78],[6,-49],[-17,-70],[4,-69]],[[4374,3152],[-7,10],[-92,42],[-58,70],[-23,56],[-69,42],[-34,-42],[-17,-42],[-29,-49],[-63,-36],[-6,0]],[[3976,3203],[-23,28],[-12,155],[-52,112],[12,127],[28,77],[81,49],[115,134],[97,49],[69,36],[40,49],[23,70],[46,28],[109,21],[64,15],[172,-42],[92,-162],[167,-175],[75,141],[55,72],[44,129],[49,101],[4,35],[-4,126]],[[5227,4378],[81,1],[86,-35],[63,-56],[47,-64],[8,-49],[3,0],[10,-5]],[[3418,6744],[23,-2],[49,-140],[140,-270],[82,-79]],[[3712,6253],[-10,-25]],[[1880,6148],[11,30],[131,60],[180,51],[189,131],[213,150],[56,35],[42,26],[189,40],[344,91],[183,-18]],[[6834,4297],[43,-183],[35,-112],[42,-71],[-32,4],[-46,0]],[[6595,3495],[-74,-127],[-51,-42],[-28,-35],[-40,-56],[-34,-55],[-40,-49]],[[5525,4170],[7,12],[69,22],[86,-14],[87,-56],[23,-21],[28,28],[-5,56],[34,42],[69,-14],[213,50],[63,42],[63,56],[57,71],[92,-21],[167,-77],[115,-28],[92,-7],[40,21],[9,-35]],[[5537,1717],[-24,-23],[-62,-28],[-51,-7],[-68,-63],[-35,-62],[-45,-77],[-23,-83],[-17,-49],[-51,-28],[-40,-21],[-34,-55],[35,-56],[11,-62],[-11,-35],[-23,-56],[-17,-35],[6,-48],[45,-56],[17,-35],[6,-83],[-23,-49],[-5,-34],[-12,-56],[12,-70],[-23,-48],[-45,-84],[-9,-38],[6,-63],[3,-13],[9,-35],[-17,-49],[-86,-125],[-91,-49],[-170,-42],[-142,7],[-48,4],[0,6],[-41,29],[-54,14],[-30,22],[-12,5]],[[9670,7218],[-86,-79],[-103,-113],[-35,-84],[-17,-105],[0,-71],[12,-84],[0,-49],[-17,-56],[-69,-57],[-46,-42],[0,-35],[14,-7],[-37,-42],[-12,-63],[-34,-43],[-28,-4]],[[9212,6284],[-24,39],[-98,85],[-17,140],[-17,56],[-69,49],[-29,134],[-35,77],[-115,35],[-86,7],[-29,42],[-57,140],[0,63],[-35,42],[11,92],[18,161],[-41,42],[-6,57],[29,161],[31,239],[46,225],[63,133],[12,64],[0,56],[-9,7]],[[8755,8430],[-6,63],[0,49],[92,56],[39,34]],[[8755,8430],[-58,21],[-74,7],[-98,-1],[-75,0],[-80,-21],[-52,-63],[-27,-84]],[[7358,8562],[11,27],[12,56],[-12,113],[-6,63],[-5,84],[28,84],[70,59],[39,33],[41,28],[46,21],[51,-14],[29,0],[92,99],[109,140],[40,43],[40,35],[23,-28],[29,-49],[29,-28],[63,35],[39,18]],[[5170,7210],[-7,-11],[9,-5],[24,-15],[151,-167],[87,-61],[72,-58],[12,-35],[11,-49],[35,-21],[77,11]],[[5289,5635],[-29,8],[6,7],[-74,-7],[-64,-8],[-74,14],[-64,7],[-28,-49],[-52,-140],[-69,-29],[-132,-21],[-46,-21],[-57,-49],[4,-65]],[[4610,5282],[-73,57],[-23,29],[-144,168],[-98,168],[-110,169],[-258,217],[-167,105],[-39,10]],[[3712,6253],[34,89],[64,141],[51,18],[179,-18],[101,9],[64,18],[29,18],[65,149],[71,114],[51,0],[72,-43],[14,-44],[-14,-79],[100,-62],[29,-52],[7,-53],[36,9],[29,26],[0,9],[36,-17],[7,-62],[43,-17],[29,26],[0,44],[22,53],[50,9],[36,-18],[21,26],[0,115],[-29,193],[-7,70],[0,61],[14,88],[22,62],[11,56],[11,52],[39,46]],[[4999,7289],[74,-15],[97,-64]],[[833,2796],[-8,37],[0,80],[-25,121],[-27,29],[2,21],[-7,100],[-9,10],[-83,120],[-8,60],[41,71],[-74,59],[0,121],[16,180],[8,131],[115,0],[49,40],[115,241],[41,20],[57,50],[66,30],[-9,60],[-24,40],[123,131],[13,17]],[[9212,6284],[-18,-3],[-34,-14],[-98,-14],[-33,-67],[-65,25],[-132,28],[-40,70],[-69,70],[-12,49],[17,42],[12,127],[-35,70],[-75,21],[-161,-50],[-75,-38]],[[8394,6600],[-34,59],[17,99],[0,98],[-34,105],[-115,-7],[-23,-7],[-52,42],[-58,49],[-51,77],[-41,113],[-17,63],[80,35],[69,21],[1,29]],[[3418,6744],[19,102],[-1,151],[9,86],[9,97],[61,108],[124,108],[115,54],[52,86],[9,76],[-88,215],[-9,86],[-9,87],[9,85],[8,76],[0,54],[27,11],[8,-4],[45,-17],[52,-11],[36,43],[0,76],[53,0],[114,-151],[151,-43],[28,-21],[86,-65],[18,-65],[18,-75],[70,-75],[80,-65],[159,-183],[133,-172],[110,-92],[85,-17]],[[4902,4836],[9,5],[155,-217],[110,-147],[51,-99]],[[3976,3203],[-63,0],[-64,63],[-51,71],[-87,27],[-40,-1]],[[3645,3672],[37,149],[0,246],[109,288],[137,267],[172,204],[75,49],[98,57],[126,-98],[207,-211],[41,-7],[132,141],[123,79]],[[4610,5282],[7,-6],[35,-49],[115,-182],[92,-119],[43,-90]],[[1225,1346],[-31,-11],[-24,-15],[-29,-80],[-30,-80],[-42,-36],[-71,0],[-155,-22],[-71,-15],[-113,-22],[-45,-11],[-79,74],[-107,19],[-66,10],[-65,90],[-66,80],[-107,60],[-65,40],[-50,60],[0,171],[-9,73],[17,17],[49,341],[90,241],[82,60],[74,20],[65,20],[58,61],[41,-20],[82,-40],[98,20],[57,30],[66,10],[60,-46]],[[8394,6600],[7,-11],[-46,-126],[-63,-232],[-115,-288],[-144,-71],[-55,-78],[15,43],[-21,9]],[[7291,5175],[10,-42],[-109,-35],[-69,-77],[-80,-106],[-161,-225],[-86,-161],[-5,-71],[46,-140],[-3,-21]],[[4097,2480],[-57,-35],[-69,-35],[-52,0],[-63,56],[-40,56],[-46,0],[-58,35],[-28,28],[-41,147],[-6,148],[-23,147],[-40,42],[-71,127]],[[4128,1738],[-12,-2],[-41,-14],[-23,-42],[-17,-43],[-40,-28],[-98,14],[-28,56],[-12,56],[23,43],[52,35],[40,42],[11,63],[-29,35],[-74,7],[-92,-14],[-23,-49],[-17,-49],[-35,-36],[-74,-35],[-41,-28],[-46,-56],[-11,-64],[0,-91],[12,-126],[-12,-56],[-17,-43],[-29,-21],[-45,-14],[-41,7],[-28,42],[-47,42],[-34,7],[-34,-14],[-29,28],[-6,49],[6,78],[5,98],[6,63],[34,49],[0,106],[-36,133]],[[3686,718],[-86,39],[-95,73],[-60,29],[-202,51],[-96,19]],[[3147,929],[10,82],[46,63],[0,98],[-6,42],[-35,21],[-80,71],[-29,21],[-23,-43],[0,-63],[-23,-63],[-40,-35],[-230,41],[-98,42],[-34,64],[-29,14],[-14,-40]],[[3147,929],[-47,9],[-77,-29],[-24,-58],[-18,-80],[-12,-29],[-89,-117],[-36,-51],[1,-44],[-6,-43],[-24,-51],[-36,-51],[-35,-15],[-30,0],[-24,22],[-24,7],[-30,-14],[-17,-30],[-36,-80],[-48,-29],[-47,-14],[-57,-52],[-35,-58],[-84,-51],[-113,-66],[-53,0],[-34,7],[-2,1],[-24,14],[-30,87],[-3,17],[-9,49],[-18,400],[-12,247],[-30,138],[-36,80],[-21,29]],[[5170,7210],[26,43],[18,43],[-27,97],[-70,119],[-18,107],[53,141],[-9,86],[26,118],[53,22],[53,0],[150,-64],[106,-65],[53,11],[88,119],[123,108],[32,15],[109,50],[106,0],[150,-10],[115,-22],[88,11],[87,16],[28,6],[88,-86],[71,-43]]],"transform":{"scale":[0.000014732290012972376,0.000012030822431735556],"translate":[80.07327638996254,7.4991555181429606]}}